stax_cx_service_sdk/__init__.py
stax_cx_service_sdk/wrapper.py
stax_cx_service_sdk-0.0.1.dist-info/LICENSE.md
stax_cx_service_sdk-0.0.1.dist-info/METADATA
stax_cx_service_sdk-0.0.1.dist-info/WHEEL
stax_cx_service_sdk-0.0.1.dist-info/top_level.txt
stax_cx_service_sdk-0.0.1.dist-info/RECORD
