Metadata-Version: 2.1
Name: stax_cx_service_sdk
Version: 0.0.1
Summary: Stax.ai CX Service SDK
Home-page: https://bitbucket.org/staxai/cx-service-sdk
Author: Stax.ai, Inc. <https://stax.ai>
Author-email: naru@stax.ai
License: Proprietary
Classifier: Programming Language :: Python :: 3
Classifier: Operating System :: OS Independent
Requires-Python: >=3.6
License-File: LICENSE.md
Requires-Dist: retry-requests
Requires-Dist: functions-framework
